td_mcp_server/__init__.py
td_mcp_server/api.py
td_mcp_server/diagnostic_tools.py
td_mcp_server/execution_tools.py
td_mcp_server/exploration_tools.py
td_mcp_server/mcp_impl.py
td_mcp_server/search_tools.py
td_mcp_server/server.py
td_mcp_server/url_tools.py
mseep_td_mcp_server-0.1.1.dist-info/METADATA
mseep_td_mcp_server-0.1.1.dist-info/WHEEL
mseep_td_mcp_server-0.1.1.dist-info/entry_points.txt
mseep_td_mcp_server-0.1.1.dist-info/top_level.txt
mseep_td_mcp_server-0.1.1.dist-info/RECORD
